quadplots/GraphQuad.py
quadplots/Interval.py
quadplots/Quadrature.py
quadplots/__init__.py
quadplots/__main__.py
quadplots-1.0.3.dist-info/LICENSE
quadplots-1.0.3.dist-info/METADATA
quadplots-1.0.3.dist-info/WHEEL
quadplots-1.0.3.dist-info/entry_points.txt
quadplots-1.0.3.dist-info/top_level.txt
quadplots-1.0.3.dist-info/RECORD
