Metadata-Version: 2.1
Name: quadplots
Version: 1.0.3
Summary: Create animations of simple numerical integration methods.
Author: Chris Copley
Project-URL: Repository, https://github.com/CopOnTheRun/quadplots
Project-URL: Issues, https://github.com/CopOnTheRun/quadplots/issues
Keywords: Simpson's Rule,Trapezoidal rule,Riemann Sum,Visualization,Graph,Quadrature
Classifier: License :: OSI Approved :: MIT License
Classifier: Programming Language :: Python
Classifier: Programming Language :: Python :: 3
Classifier: Intended Audience :: Education
Requires-Python: >=3.10
License-File: LICENSE
Requires-Dist: matplotlib
Requires-Dist: numpy
Requires-Dist: sympy
Requires-Dist: antlr4-python3-runtime ==4.11
Provides-Extra: build
Requires-Dist: build ; extra == 'build'
Requires-Dist: twine ; extra == 'build'
Provides-Extra: dev
Requires-Dist: bumpver ; extra == 'dev'
Requires-Dist: mypy ; extra == 'dev'
Requires-Dist: uv ; extra == 'dev'
